pagemap/__init__.py
pagemap/constant.py
pagemap/entry.py
pagemap/hexint.py
pagemap/row.py
pagemap/utils.py
pagemap-0.1.1.dist-info/entry_points.txt
pagemap-0.1.1.dist-info/LICENSE
pagemap-0.1.1.dist-info/WHEEL
pagemap-0.1.1.dist-info/METADATA
pagemap-0.1.1.dist-info/RECORD
