Metadata-Version: 2.1
Name: pagemap
Version: 0.1.1
Summary: A tool for virtual memory.
License: MIT
Keywords: pagemap,maps,linux
Author: fffzlfk
Author-email: 1319933925qq@gmail.com
Requires-Python: >=3.9,<4.0
Classifier: License :: OSI Approved :: MIT License
Classifier: Programming Language :: Python :: 3
Classifier: Programming Language :: Python :: 3.10
Classifier: Programming Language :: Python :: 3.9
Requires-Dist: click (>=8.1,<9.0)
